principle_alignment/__init__.py
principle_alignment/alignment.py
principle_alignment/serving.py
principle_alignment/utilities/logger.py
principle_alignment/utilities/printer.py
principle_alignment-0.1.10.dist-info/LICENSE
principle_alignment-0.1.10.dist-info/METADATA
principle_alignment-0.1.10.dist-info/WHEEL
principle_alignment-0.1.10.dist-info/top_level.txt
principle_alignment-0.1.10.dist-info/RECORD
