Metadata-Version: 2.2
Name: principle-alignment
Version: 0.1.10
Summary: principle alignment package
Author-email: ZJun <zhangjun310@live.com>
License: MIT
Project-URL: Repository, https://github.com/ZJCODE/principle-alignment
Classifier: Programming Language :: Python :: 3
Classifier: License :: OSI Approved :: MIT License
Classifier: Operating System :: OS Independent
Requires-Python: >=3.10
License-File: LICENSE
Requires-Dist: fastapi
Requires-Dist: uvicorn
Requires-Dist: pyyaml
Requires-Dist: openai
Requires-Dist: python-dotenv
Requires-Dist: tenacity
Requires-Dist: requests
